LICENSE
MANIFEST.in
README.md
setup.py
django_google_urchin.egg-info/PKG-INFO
django_google_urchin.egg-info/SOURCES.txt
django_google_urchin.egg-info/dependency_links.txt
django_google_urchin.egg-info/requires.txt
django_google_urchin.egg-info/top_level.txt
google_analytics/__init__.py
google_analytics/models.py
google_analytics/views.py
google_analytics/templatetags/__init__.py
google_analytics/templatetags/analytics.py