Metadata-Version: 1.0
Name: django-google-urchin
Version: 0.1a1
Summary: Provides a Django template tag to insert the Google Analytics tracking code.
Home-page: https://bitbucket.org/nextscreenlabs/django-google-analytics
Author: Jason Christa
Author-email: jason@zeitcode.com
License: UNKNOWN
Platform: UNKNOWN
Classifier: Environment :: Web Environment
Classifier: License :: OSI Approved :: BSD License
Classifier: Framework :: Django
Classifier: Programming Language :: Python
